.editorconfig
.gitignore
.travis.yml
CONTRIBUTING.rst
LICENSE
MANIFEST.in
README.rst
requirements_dev.txt
setup.py
tox.ini
data/info.armills.SymbolPlease.desktop
data/symbol_please.png
data/raw/all_spells.json
data/raw/class/Bard
data/raw/class/Cleric
data/raw/class/Druid
data/raw/class/Enchanter
data/raw/class/Magician
data/raw/class/Monk
data/raw/class/Necromancer
data/raw/class/Paladin
data/raw/class/Ranger
data/raw/class/Rogue
data/raw/class/Shadow_Knight
data/raw/class/Shaman
data/raw/class/Warrior
data/raw/class/Wizard
data/raw/spell/Aanyas Animation
data/raw/spell/Aanyas Quickening
data/raw/spell/Abolish Disease
data/raw/spell/Abolish Poison
data/raw/spell/Abscond
data/raw/spell/Abundant Drink
data/raw/spell/Abundant Food
data/raw/spell/Acumen
data/raw/spell/Adorning Grace
data/raw/spell/Aegis
data/raw/spell/Aegis of Ro
data/raw/spell/Aegolism
data/raw/spell/Affliction
data/raw/spell/Agility
data/raw/spell/Alacrity
data/raw/spell/Alliance
data/raw/spell/Allure
data/raw/spell/Allure of Death
data/raw/spell/Allure of the Wild
data/raw/spell/Alluring Aura
data/raw/spell/Alter Plane Hate
data/raw/spell/Alter Plane Sky
data/raw/spell/Anarchy
data/raw/spell/Animate Dead
data/raw/spell/Annul Magic
data/raw/spell/Antidote
data/raw/spell/Arch Lich
data/raw/spell/Arch Shielding
data/raw/spell/Armor of Faith
data/raw/spell/Armor of Protection
data/raw/spell/Asphyxiate
data/raw/spell/Assiduous Vision
data/raw/spell/Asystole
data/raw/spell/Atols Spectral Shackles
data/raw/spell/Atone
data/raw/spell/Augment
data/raw/spell/Augment Death
data/raw/spell/Augmentation
data/raw/spell/Augmentation of Death
data/raw/spell/Avalanche
data/raw/spell/Avatar
data/raw/spell/Bandoleer of Luclin
data/raw/spell/Bane of Nife
data/raw/spell/Banish Summoned
data/raw/spell/Banish Undead
data/raw/spell/Banishment
data/raw/spell/Banishment of Shadows
data/raw/spell/Banshee Aura
data/raw/spell/Barbcoat
data/raw/spell/Barrier of Combustion
data/raw/spell/Bedlam
data/raw/spell/Befriend Animal
symbol_please.egg-info/PKG-INFO
symbol_please.egg-info/SOURCES.txt
symbol_please.egg-info/dependency_links.txt
symbol_please.egg-info/entry_points.txt
symbol_please.egg-info/not-zip-safe
symbol_please.egg-info/requires.txt
symbol_please.egg-info/top_level.txt
