Metadata-Version: 1.1
Name: symbol-please
Version: 1.1.1
Summary: Symbol Please is a visual log parsing helper for Project 1999
Home-page: https://gitlab.com/armills/symbol_please
Author: Adam Mills
Author-email: adam@armills.info
License: Apache Software License 2.0
Keywords: symbol_please
Platform: UNKNOWN
Classifier: Development Status :: 5 - Production/Stable
Classifier: Environment :: X11 Applications :: GTK
Classifier: Intended Audience :: End Users/Desktop
Classifier: License :: OSI Approved :: Apache Software License
Classifier: Natural Language :: English
Classifier: Programming Language :: Python :: 3.6
